README.md
setup.py
src/s3local/__init__.py
src/s3local/commands.py
src/s3local/constants.py
src/s3local/core.py
src/s3local/downloader.py
src/s3local/logger.py
src/s3local/uploader.py
src/s3local/util.py
src/s3local.egg-info/PKG-INFO
src/s3local.egg-info/SOURCES.txt
src/s3local.egg-info/dependency_links.txt
src/s3local.egg-info/entry_points.txt
src/s3local.egg-info/not-zip-safe
src/s3local.egg-info/requires.txt
src/s3local.egg-info/top_level.txt
tests/test_commands.py
tests/test_util.py