Metadata-Version: 2.1
Name: s3local
Version: 0.4.2
Summary: Command Line utility for s3 local caching.
Home-page: https://github.com/toyama0919/s3local
Author: Hiroshi Toyama
Author-email: toyama0919@gmail.com
License: MIT
Keywords: s3local tool aws s3
Classifier: Programming Language :: Python :: 3.7
Classifier: Programming Language :: Python :: 3.8
Classifier: Programming Language :: Python :: 3.9
Classifier: Programming Language :: Python :: 3.10
Classifier: Programming Language :: Python :: 3.11
Provides-Extra: test
